{"school year": ["2003 - 04", "2004 - 05", "2005 - 06", "2006 - 07", "2007 - 08", "2008 - 09", "2009 - 10", "2010 - 11", "2011 - 12", "2012 - 13"], "volleyball": ["orrville", "orrville , madison , lexington , west holmes", "wooster", "wooster", "wooster", "madison", "lexington , madison , orrville", "madison", "madison", "lexington"], "cross country": ["ashland", "ashland", "lexington", "ashland", "lexington", "wooster", "lexington", "lexington", "lexington", "lexington"], "soccer": ["lexington", "ashland", "ashland", "ashland", "ashland", "ashland", "lexington , wooster", "clear fork", "wooster", "ashland"], "tennis": ["lexington", "lexington", "lexington", "lexington", "lexington", "lexington", "lexington", "lexington", "lexington", "lexington"], "golf": ["began in 2013", "n / a", "n / a", "n / a", "n / a", "n / a", "n / a", "n / a", "n / a", "n / a"], "basketball": ["orrville", "orrville", "wooster", "lexington", "west holmes", "west holmes", "orrville", "west holmes", "west holmes", "west holmes"], "swimming": ["wooster", "lexington", "wooster", "wooster", "wooster", "wooster", "wooster", "lexington", "wooster", "wooster"], "softball": ["ashland", "lexington", "clear fork", "ashland", "clear fork , wooster", "clear fork , lexington", "clear fork", "clear fork", "orrville", "madison"], "track & field": ["lexington", "lexington", "ashland", "ashland", "orrville", "ashland", "ashland", "ashland", "orrville", "west holmes"]}