{"district": ["alabama 1", "alabama 2", "alabama 4", "alabama 5", "alabama 6"], "incumbent": ["jo bonner", "terry everett", "robert aderholt", "robert cramer", "spencer bachus"], "party": ["republican", "republican", "republican", "democratic", "republican"], "first elected": ["2002", "1992", "1996", "1990", "1992"], "results": ["re - elected", "re - elected", "re - elected", "re - elected", "re - elected"], "candidates": ["jo bonner (r) 68.1% vivian beckerle (d) 31.8%", "terry everett (r) 69.5% chuck james (d) 30.4%", "robert aderholt (r) 70.2% barbara bobo (d) 29.7%", "robert cramer (d) unopposed", "spencer bachus (r) unopposed"]}