{"year (ceremony)": ["1989 (62nd)", "1992 (65th)", "1993 (66th)", "1994 (67th)", "1997 (70th)", "1999 (72nd)", "2000 (73rd)", "2001 (74th)", "2002 (75th)", "2003 (76th)", "2005 (78th)", "2006 (79th)", "2007 (80th)", "2008 (81st)", "2009 (82nd)", "2010 (83rd)", "2011 (84th)", "2012 (85th)"], "film title used in nomination": ["don't let them shoot the kite", "piano piano kid", "the blue exile", "tarzan of manisa", "the bandit", "mrs salkım 's diamonds", "run for money", "hejar", "9", "distant", "lovelorn", "ice cream , i scream", "a man 's fear of god", "three monkeys", "i saw the sun", "honey", "once upon a time in anatolia", "where the fire burns"], "original title": ["uçurtmayı vurmasınlar", "piyano piyano bacaksız", "mavi sürgün", "manisa tarzanı", "eşkıya", "salkım hanımın taneleri", "kaç para kaç", "büyük adam küçük aşk", "9", "uzak", "gönül yarası", "dondurmam gaymak", "takva", "üç maymun", "güneşi gördüm", "bal", "bir zamanlar anadolu'da", "ateşin düştüğü yer"], "director": ["tunç başaran", "tunç başaran", "erden kıral", "orhan oğuz", "yavuz turgul", "tomris giritlioğlu", "reha erdem", "handan ipekçi", "ümit ünal", "nuri bilge ceylan", "yavuz turgul", "yüksel aksu", "özer kızıltan", "nuri bilge ceylan", "mahsun kırmızıgül", "semih kaplanoğlu", "nuri bilge ceylan", "ismail güneş"], "result": ["not nominated", "not nominated", "not nominated", "not nominated", "not nominated", "not nominated", "not nominated", "not nominated", "not nominated", "not nominated", "not nominated", "not nominated", "not nominated", "made january shortlist", "not nominated", "not nominated", "not nominated", "not nominated"]}