{"draw": ["1", "2", "3", "4", "5", "6", "7", "8", "9", "10", "11", "12", "13", "14"], "artist": ["alexei krechet", "petr elfimov", "cola feat lidiya zablotskaya", "singerin", "dakota (дакота)", "the champions", "alex patlis band", "litesound feat dakota", "dominica", "dyada vanya", "veter v golove", "anna blagova & yury vashchuk", "gunesh", "victoria belova"], "original": ["joy and freedom", "eyes that never lie", "гудок (gudok)", "don't think about it", "цябе забываю (ciabie zabyvaju )", "shake it , europe", "кто сказал (kto skazal)", "carry on", "this is my day", "наша belarussia (nasha belarussia)", "or or and", "behind", "fantastic girl", "don't give up from love"], "english meaning": ["joy and freedom", "eyes that never lie", "dial tone", "don't think about it", "im forgetting you", "shake it , europe", "who said", "carry on", "this is my day", "our belarussia", "or or and", "behind", "fantastic girl", "don't give up from love"], "language": ["english", "english", "russian", "english", "belarusian", "english", "russian", "english", "english", "russian", "english", "english", "english", "english"], "authors": ["v ruzov , a shenets", "p elfimov , v prokhozhy", "gridin , v shevchenko", "k dudich", "dakota , g lobodenko", "nils , o orakposim", "alex patlis", "v karyakin", "s sukhomlin , a kostugov", "i vabishchevich", "a zakharik , g galushko", "y vashchuk , a zhilina", "gunesh , m khaitbayeva", "a klimka , v belova"]}