{"round": ["1", "2", "3", "4", "5", "6", "7", "8", "9", "10"], "pick": ["6", "24", "48", "69", "87", "108", "129", "150", "171", "191"], "player": ["craig redmond", "brian wilks", "john english", "tom glavine", "david grannis", "greg strome", "timothy hanley", "shannon deegan", "luc robitaille", "jeff crossman"], "position": ["defence", "centre", "defence", "centre", "left wing", "goaltender", "centre", "centre", "left wing", "centre"], "nationality": ["canada", "canada", "canada", "united states", "united states", "canada", "united states", "canada", "canada", "canada"], "college / junior / club team": ["university of denver ( wcha )", "kitchener rangers (ohl)", "sault ste marie greyhounds (ohl)", "billerica high school (massachusetts)", "south st paul high school (minnesota)", "university of north dakota (wcha)", "deerfield academy (massachusetts)", "university of vermont (ecac)", "hull olympiques (qmjhl)", "western michigan university (ccha)"]}