{"episode": ["audition", "bootcamp", "bootcamp", "bootcamp", "bootcamp", "live show 1", "live show 2", "live show 3", "live show 4", "live show 5", "live show 6", "live show 7", "live show 8", "live show 8", "live show 9", "live show 10", "live show 10", "live show 11", "live show 11", "live show 12", "live show 12", "live show 12", "final", "final", "final"], "theme": ["auditioner 's choice", "auditioner 's choice", "auditioner 's choice", "auditioner 's choice", "auditioner 's choice", "mentor 's choice", "mentor 's choice", "1980s in music", "mentor 's choice", "mentor 's choice", "mentor 's choice", "mentor 's choice", "mentor 's choice", "acappella songs", "sanremo music festival", "italian - language songs", "michael jackson", "mentor 's choice", "mentor 's choice", "mentor 's choice", "acappella songs", "winner 's song", "celebrity duets", "mentor 's choice", "winner 's song"], "song choice": ["uomini semplici", "la luce dell'est", "we can work it out", "(you make me feel like) a natural woman", "i'm outta love", "man in the mirror", "l'amore si odia", "notorious", "psycho killer", "my baby just cares for me", "ashes to ashes", "helter skelter", "insieme a te sto bene", "l'appuntamento", "almeno tu nell'universo", "onda su onda", "billie jean", "kiss", "il nostro concerto", "back in black", "senza fine", "dove si vola", "oggi sono io (with alex britti)", "amore assurdo", "dove si vola"], "original artist": ["eduardo de crescenzo", "lucio battisti", "the beatles", "aretha franklin", "anastacia", "michael jackson", "noemi feat fiorella mannoia", "duran duran", "talking heads", "nina simone", "david bowie", "the beatles", "lucio battisti", "ornella vanoni", "mia martini", "bruno lauzi", "michael jackson", "prince and the revolution", "umberto bindi", "ac / dc", "gino paoli", "marco mengoni", "alex britti", "morgan", "marco mengoni"], "order": ["n / a", "n / a", "n / a", "n / a", "n / a", "5", "2", "1", "6", "4", "5", "3", "2", "12", "6", "1", "11", "5", "6", "4", "5", "12", "3", "5", "7"], "result": ["advanced", "advanced", "advanced", "advanced", "advanced", "safe", "safe", "safe", "safe", "safe", "safe", "safe", "safe", "safe", "safe", "safe", "safe", "safe", "safe", "safe", "safe", "safe", "safe", "safe", "safe"]}