{"week": ["1", "2", "3", "4", "5", "6", "7", "8", "9", "10", "11", "12", "13", "14"], "date": ["september 15 , 1963", "september 22 , 1963", "september 29 , 1963", "october 5 , 1963", "october 13 , 1963", "october 20 , 1963", "october 27 , 1963", "november 3 , 1963", "november 10 , 1963", "november 17 , 1963", "november 24 , 1963", "december 1 , 1963", "december 8 , 1963", "december 15 , 1963"], "opponent": ["washington redskins", "dallas cowboys", "los angeles rams", "pittsburgh steelers", "new york giants", "philadelphia eagles", "new york giants", "philadelphia eagles", "pittsburgh steelers", "st louis cardinals", "dallas cowboys", "st louis cardinals", "detroit lions", "washington redskins"], "result": ["w 37 - 14", "w 41 - 24", "w 20 - 6", "w 35 - 23", "w 35 - 24", "w 37 - 7", "l 33 - 6", "w 23 - 17", "l 9 - 7", "l 20 - 14", "w 27 - 17", "w 24 - 10", "l 38 - 10", "w 27 - 20"], "attendance": ["57618", "28710", "54713", "84684", "62956", "75174", "84213", "60671", "54497", "75932", "55096", "32531", "51382", "40865"]}