{"home team": ["essendon", "collingwood", "carlton", "south melbourne", "melbourne", "footscray"], "home team score": ["8.15 (63)", "9.24 (78)", "9.12 (66)", "12.11 (83)", "11.12 (78)", "17.13 (115)"], "away team": ["richmond", "hawthorn", "st kilda", "north melbourne", "geelong", "fitzroy"], "away team score": ["7.12 (54)", "6.11 (47)", "7.12 (54)", "11.14 (80)", "15.9 (99)", "10.8 (68)"], "venue": ["windy hill", "victoria park", "princes park", "lake oval", "mcg", "western oval"], "crowd": ["16957", "31923", "22154", "9461", "23557", "11603"], "date": ["28 june 1969", "28 june 1969", "28 june 1969", "28 june 1969", "28 june 1969", "28 june 1969"]}