{"model name": ["happy hacking keyboard", "happy hacking keyboard", "happy hacking keyboard lite", "happy hacking keyboard lite 2", "happy hacking keyboard lite 2", "happy hacking keyboard lite 2", "happy hacking keyboard lite 2", "happy hacking keyboard lite 2", "happy hacking keyboard lite 2", "happy hacking keyboard lite 2", "happy hacking keyboard lite 2", "happy hacking keyboard lite 2", "happy hacking keyboard lite 2", "happy hacking keyboard lite 2", "happy hacking keyboard lite 2", "happy hacking keyboard professional", "happy hacking keyboard professional", "happy hacking keyboard professional", "happy hacking keyboard professional", "happy hacking keyboard professional 2", "happy hacking keyboard professional 2", "happy hacking keyboard professional 2", "happy hacking keyboard professional 2", "happy hacking keyboard professional jp", "happy hacking keyboard professional jp", "happy hacking keyboard professional hg", "happy hacking keyboard professional hg", "happy hacking keyboard professional hg", "happy hacking keyboard professional hg", "happy hacking keyboard professional hg japan", "happy hacking keyboard professional 2 type - s", "happy hacking keyboard professional 2 type - s", "happy hacking keyboard professional jp type - s"], "model": ["pd - kb02", "pd - kb02n", "pd - kb100w", "pd - kb200w / p", "pd - kb200b / p", "pd - kb200w / u", "pd - kb200b / u", "pd - kb210w / u", "pd - kb210b / u", "pd - kb220w / u", "pd - kb220b / u", "pd - kb220 mkw", "pd - kb200 mkb", "pd - kb200 ma", "pd - kb220 ma", "pd - kb300", "pd - kb300b", "pd - kb300nl", "pd - kb300bn", "pd - kb400w", "pd - kb400b", "pd - kb400wn", "pd - kb400bn", "pd - kb420w", "pd - kb420b", "pd - kb500w", "pd - kb500b", "pd - kb500wn", "pd - kb500bn", "pd - kb500j", "pd - kb400ws", "pd - kb400wns", "pd - kb420ws"], "color": ["white", "white", "white", "white", "black", "white", "black", "white", "black", "white", "black", "white", "black", "white", "white", "white", "charcoal gray", "white", "charcoal gray", "white", "charcoal gray", "white", "charcoal gray", "white", "charcoal gray", "white", "black", "white", "black", "wajima - style lacquer", "white", "white", "white"], "switch type": ["membrane", "membrane", "membrane", "membrane", "membrane", "membrane", "membrane", "membrane", "membrane", "membrane", "membrane", "membrane", "membrane", "membrane", "membrane", "capacitive", "capacitive", "capacitive", "capacitive", "capacitive", "capacitive", "capacitive", "capacitive", "capacitive", "capacitive", "capacitive", "capacitive", "capacitive", "capacitive", "capacitive", "capacitive", "capacitive", "capacitive"], "interface": ["ps / 2 , sun , adb", "ps / 2 , sun , adb", "ps / 2", "ps / 2", "ps / 2", "usb", "usb", "usb", "usb", "usb", "usb", "usb", "usb", "usb", "usb", "usb", "usb", "usb", "usb", "usb", "usb", "usb", "usb", "usb", "usb", "usb", "usb", "usb", "usb", "usb", "usb", "usb", "usb"], "blank keytops": ["no", "no", "no", "no", "no", "no", "no", "no", "no", "no", "no", "no", "no", "no", "no", "no", "no", "yes", "yes", "no", "no", "yes", "yes", "no", "no", "no", "no", "yes", "yes", "yes", "no", "yes", "no"], "introduced": ["dec 20 , 1996", "dec 20 , 1996", "jun 7 , 1999", "mar 15 , 2001", "mar 15 , 2001", "mar 15 , 2001", "mar 15 , 2001", "mar 15 , 2001", "mar 15 , 2001", "mar 15 , 2001", "mar 15 , 2001", "mar 15 , 2001", "mar 15 , 2001", "mar 15 , 2001", "mar 15 , 2001", "apr 24 , 2003", "apr 24 , 2003", "apr 24 , 2003", "apr 24 , 2003", "mar 24 , 2006", "mar 24 , 2006", "mar 24 , 2006", "mar 24 , 2006", "nov 10 , 2008", "nov 10 , 2008", "oct 12 , 2006", "oct 12 , 2006", "oct 12 , 2006", "oct 12 , 2006", "oct 12 , 2006", "june 29 , 2011", "june 29 , 2011", "june 29 , 2011"]}