{"date": ["august 1", "august 2", "august 2", "august 3", "august 4", "august 5", "august 6", "august 7", "august 8", "august 8", "august 9", "august 10", "august 11", "august 12", "august 13", "august 14", "august 15", "august 16", "august 16", "august 17", "august 19", "august 20", "august 21", "august 22", "august 23", "august 24", "august 25", "august 26", "august 27", "august 28", "august 29", "august 29", "august 30", "august 31"], "opponent": ["indians", "yankees", "yankees", "yankees", "yankees", "brewers", "brewers", "brewers", "yankees", "yankees", "yankees", "yankees", "brewers", "brewers", "brewers", "brewers", "indians", "indians", "indians", "indians", "red sox", "red sox", "red sox", "red sox", "orioles", "orioles", "orioles", "tigers", "tigers", "tigers", "red sox", "red sox", "red sox", "orioles"], "score": ["6 - 0", "10 - 9 (10)", "13 - 6", "6 - 2", "3 - 1", "7 - 0", "3 - 0", "9 - 6", "8 - 3", "11 - 3", "8 - 0", "8 - 3", "6 - 4", "5 - 4", "3 - 1", "4 - 3", "3 - 2", "3 - 2", "9 - 6", "6 - 5 (10)", "8 - 7", "5 - 2", "7 - 3", "4 - 2", "9 - 3", "7 - 4 (10)", "2 - 1 (10)", "4 - 3 (10)", "7 - 4", "4 - 2", "5 - 1", "8 - 7", "5 - 4 (12)", "10 - 2"], "loss": ["alexander (0 - 5)", "murray (2 - 2)", "shirley (3 - 6)", "guidry (12 - 7)", "stieb (11 - 10)", "gott (6 - 9)", "alexander (0 - 6)", "leal (10 - 10)", "clancy (12 - 7)", "williams (1 - 1)", "rawley (10 - 10)", "gott (6 - 10)", "alexander (0 - 7)", "slaton (9 - 5)", "mcclure (9 - 9)", "ladd (3 - 3)", "spillner (1 - 8)", "moffitt (6 - 1)", "anderson (0 - 4)", "sutcliffe (13 - 9)", "clear (3 - 5)", "stieb (13 - 11)", "hurst (9 - 10)", "alexander (0 - 8)", "flanagan (7 - 3)", "mclaughlin (7 - 3)", "jackson (8 - 2)", "gott (7 - 11)", "lopez (8 - 6)", "mclaughlin (7 - 4)", "tudor (10 - 9)", "moffitt (6 - 2)", "jackson (8 - 3)", "gott (7 - 12)"], "record": ["57 - 44", "58 - 44", "59 - 44", "60 - 44", "60 - 45", "60 - 46", "60 - 47", "60 - 48", "60 - 49", "60 - 50", "61 - 50", "61 - 51", "61 - 52", "62 - 52", "63 - 52", "64 - 52", "65 - 52", "65 - 53", "66 - 53", "67 - 53", "68 - 53", "68 - 54", "69 - 54", "69 - 55", "70 - 55", "70 - 56", "70 - 57", "70 - 58", "71 - 58", "71 - 59", "72 - 59", "72 - 60", "72 - 61", "72 - 62"]}