{"year": ["1989", "1990", "1991", "1993", "1994", "1995", "1997", "1998", "1999", "2001", "2002", "2003", "2005", "2006"], "place": ["montecatini terme", "moscow", "perth", "barcelona", "fagnano", "nicosia", "lima", "barcelona", "tampere", "cairo", "lahti", "nicosia", "lonato", "zagreb"], "gold": ["roberta morara ( ita )", "satu pusila ( fin )", "satu pusila ( fin )", "frances strodtman ( usa )", "satu pusila ( fin )", "deborah gelisio ( ita )", "deborah gelisio ( ita )", "deborah gelisio ( ita )", "pia julin ( fin )", "yafei zhang ( chn )", "yi chun lin ( tpe )", "marã­a quintanal ( esp )", "jing lin wang ( chn )", "hye kyoung son ( kor )"], "silver": ["roberta pelosi ( ita )", "elena shishirina ( urs )", "elena tkach ( urs )", "deena julin ( usa )", "elena shishirina ( rus )", "gema usieto ( esp )", "cynthia meyer ( can )", "kimberly rhode ( usa )", "pia hansen ( swe )", "yi chun lin ( tpe )", "jing lin wang ( chn )", "fang chen ( chn )", "qingnian li ( chn )", "yuxiang li ( chn )"], "bronze": ["anna maria bianchi ( ita )", "audrey grosch ( usa )", "deena julin ( usa )", "anna maria di giovanni ( ita )", "svetlana demina ( rus )", "xiang xu ( chn )", "riitta - mari murtoniemi ( fin )", "cindy gentry ( usa )", "yoshiko miura ( jpn )", "qingnian li ( chn )", "hye kyoung son ( kor )", "jing lin wang ( chn )", "monica girotto ( ita )", "bo na lee ( kor )"]}