{"year": ["1965", "1966", "1967", "1968", "1969", "1970", "1971", "1972", "1973", "1974", "1975", "1976", "1977", "1978", "1979", "1980", "1981", "1982", "1983", "1984", "1985", "1986", "1987", "1988", "1989", "1990", "1991", "1992"], "men 's singles": ["miroslav pezlar", "jan novotný", "ladislav rehor", "petr pavel", "petr pavel", "petr pavel", "miroslav šrámek", "miroslav šrámek", "karel myskovsky", "karel lakomý", "karel lakomý", "michal malý", "michal malý", "ladislav tandler", "lubomir cechovský", "richard hobzik", "richard hobzik", "jiří dufek", "roman janostik", "radek heger", "tomasz mendrek", "tomasz mendrek", "radek svoboda", "martin kulhavy", "petr janda", "petr janda", "martin skoupil", "jan kostelecký"], "women 's singles": ["vera perinová", "hana rerichová", "milena kuzelová", "jaroslava krahulcová", "jaroslava krahulcová", "marie krkošková", "marie krkošková", "marie krkošková", "marie krkošková", "maria holobradá", "helena turcinková", "jirina hubertová", "zuzana valečková", "alena nejedlová", "alena nejedlová", "eliška klučková", "jitka cuprová", "irena ferencová", "jaroslava balcarová", "jaroslava balcarová", "jitka lacinová", "jitka lacinová", "jitka lacinová", "eva lacinová", "veronika vopalenska", "veronika vopalenska", "marketa koudelková", "marketa koudelková"], "men 's doubles": ["miroslav pezlar / ladislav rehor", "miroslav pezlar / ladislav rehor", "jan chmela / jiří chmela", "josef brejcha / petr freimann", "tomas dohnal / petr pavel", "zdenek kozesnik / josef kraus", "zdenek kozesnik / mojmir skalický", "miroslav šrámek / ales guttenberger", "j reis / j vachna", "karel lakomý / vladimir janda", "karel lakomý / vladimir janda", "vladimir janda / lubos sedlak", "michal malý / ladislav tandler", "juraj lenart / ladislav tandler", "petr cech / vladimir hrubý", "radek goldmann / richard hobzik", "jiří dufek / richard hobzik", "jiří dufek / tomas zapletal", "jiří hlavaty / pavel kubis", "radek heger / roman janostik", "pavel brazda / tomasz mendrek", "radek svoboda / tomasz mendrek", "radek svoboda / martin vrkoslav", "radek gregor / jan jurka", "petr janda / petr horsky", "petr janda / daniel gaspar", "jan lanik / pavel weigner", "jan kostelecký / jan panos"], "women 's doubles": ["vera perinová / miluse bilciková", "dana povolná / milena kuzelová", "milena kuzelová / alexandra fadrna", "jaroslava krahulcová / anna skodová", "marie krkošková / vera mydlarová", "jaroslava krahulcová / anna skodová", "marie krkošková / olga zrnová", "tatjana pravdová / olga zrnová", "marie krkošková / jitka trminková", "maria holobradá / helena turcinková", "helena turcinková / buresová", "helena turcinková / jirina hubertová", "milena hamralová / zuzana valečková", "milena hamralová / alena nejedlová", "eliška klučková / alena nejedlová", "sona karwaczyková / eliška klučková", "irena ferencová / yweta trminková", "jaroslava balcarová / irena ferencová", "jaroslava balcarová / jana drapaková", "jaroslava balcarová / jana mrstinová", "radka viktorinová / jitka lacinová", "eva lacinová / jitka lacinová", "eva lacinová / jitka lacinová", "eva lacinová / dana matoušková", "petra hlubučková / dana matoušková", "veronika vopalenska / diana stadniková", "marketa koudelková / zuzana kalivodová", "marketa koudelková / zuzana kalivodová"], "mixed doubles": ["petr nadvorník / vera perinová", "jan novotný / hana rerichová", "zbynek schwarz / jaroslava krahulcová", "petr freimann / benediktová", "petr pavel / jaroslava krahulcová", "petr pavel / jaroslava krahulcová", "mojmir skalicky / marie krkošková", "miroslav šrámek / olga zrnová", "karel myskovsky / marie krkošková", "vladimir janda / helena turcinková", "karel lakomý / zuzana valečková", "michal malý / zuzana valečková", "michal malý / zuzana valečková", "ladislav tandler / alena nejedlová", "stanislav kraus / alena nejedlová", "richard hobzik / eliška klučková", "richard hobzik / jitka cuprová", "jiří dufek / irena ferencová", "jiří hlavaty / radka viktorinová", "jaroslav hawlik / jaroslava balcarová", "tomasz mendrek / radka viktorinová", "tomasz mendrek / jitka lacinová", "martin vrkoslav / jitka lacinová", "jan doucha / eva lacinová", "petr janda / dana matoušková", "ladislav oros / eva melounová", "igor paar / zuzana kalivodová", "martin panos / zuzana kalivodová"]}