{"year": ["2005", "2005", "2006", "2006", "2007", "2007", "2007", "2007", "2007", "2008", "2008", "2009", "2009", "2010", "2010", "2010", "2011", "2011", "2011", "2012", "2012"], "drivers": ["neel jani", "borja garcia", "adam carroll", "javier villa", "javier villa", "sérgio jimenez", "ernesto viso", "filipe albuquerque", "marcos martinez ucha", "javier villa", "giorgio pantano", "lucas di grassi", "dani clos", "dani clos", "christian vietoris", "ho - pin tung", "dani clos", "christian vietoris", "álvaro parente", "fabio leimer", "nathanaël berthon"], "races": ["23", "22", "21", "21", "21", "5", "3", "2", "8", "20", "20", "20", "20", "20", "18", "2", "18", "14", "4", "24", "24"], "wins": ["2", "0", "0", "0", "3", "0", "0", "0", "0", "0", "4", "1", "0", "1", "1", "0", "0", "2", "0", "0", "0"], "poles": ["1", "0", "0", "0", "0", "0", "0", "0", "0", "0", "4", "1", "0", "1", "0", "0", "0", "1", "0", "1", "0"], "fl": ["0", "0", "0", "0", "0", "0", "0", "0", "0", "0", "4", "1", "0", "1", "0", "0", "0", "2", "0", "2", "0"], "points": ["48", "17.5", "33", "0", "42", "4", "0", "0", "5", "8", "76", "63", "4", "51", "29", "0", "30", "35", "8", "152", "60"], "dc": ["7th", "14th", "8th", "26th", "5th", "24th", "29th", "32nd", "22nd", "17th", "1st", "3rd", "21st", "4th", "9th", "28th", "9th", "7th", "16th", "7th", "12th"], "tc": ["5th", "5th", "7th", "7th", "6th", "6th", "6th", "6th", "6th", "4th", "4th", "4th", "4th", "4th", "4th", "4th", "3rd", "3rd", "3rd", "4th", "4th"]}