{"player": ["gerald paddio", "ruben patterson", "gary payton", "sam perkins", "chuck person", "johan petro", "mike phelps", "ricky pierce", "olden polynice", "david pope", "vitaly potapenko"], "nationality": ["united states", "united states", "united states", "united states", "united states", "france", "united states", "united states", "haiti", "united states", "ukraine"], "jersey number (s)": ["21", "21", "2 , 20", "14", "45", "27", "25", "21 , 22", "23 , 0", "51", "9"], "position": ["sf / sg", "sf", "guard", "c", "sf", "c", "sg", "sg / sf", "c", "f", "c"], "years": ["1992 - 1993", "1999 - 2001", "1990 - 2003", "1993 - 1998", "1999 - 2000", "2005 - 2007", "1986 - 1987", "1991 - 1994", "1988 - 1991 1999", "1986", "2003 - 2006"], "from": ["unlv", "cincinnati", "oregon state", "north carolina", "auburn", "pau - orthez", "alcorn state", "rice", "virginia", "norfolk state", "wright state"]}