{"date": ["september 28", "october 5", "october 12", "october 19", "october 26", "november 2", "november 9", "november 16", "november 23", "january 1"], "opponent": ["tcu", "washington", "illinois", "indiana", "wisconsin", "northwestern", "purdue", "5 iowa", "19 michigan", "oregon"], "site": ["ohio stadium columbus , oh", "husky stadium seattle , wa", "ohio stadium columbus , oh", "ohio stadium columbus , oh", "camp randall stadium madison , wi", "ohio stadium columbus , oh", "ohio stadium columbus , oh", "ohio stadium columbus , oh", "michigan stadium ann arbor , mi", "rose bowl pasadena , ca ( rose bowl )"], "result": ["l14 - 18", "w35 - 7", "w21 - 7", "w56 - 0", "w16 - 13", "w47 - 6", "w20 - 7", "w17 - 13", "w31 - 14", "w10 - 7"], "attendance": ["81784", "37500", "82239", "78348", "51051", "79635", "79177", "82935", "101001", "98202"]}