{"place": ["1", "t2", "t2", "t2", "t5", "t5", "t5", "t5", "t5", "t5"], "player": ["gary player", "lee trevino", "jim colbert", "raymond floyd", "jack nicklaus", "johnny miller", "arnold palmer", "gene littler", "bob charles", "ralph johnston"], "country": ["south africa", "united states", "united states", "united states", "united states", "united states", "united states", "united states", "new zealand", "united states"], "score": ["67", "70", "70", "70", "71", "71", "71", "71", "71", "71"], "to par": ["- 4", "- 1", "- 1", "- 1", "e", "e", "e", "e", "e", "e"]}