{"race": ["australian grand prix", "bahrain grand prix", "belgian grand prix", "brazilian grand prix", "british grand prix", "canadian grand prix", "chinese grand prix", "french grand prix", "hungarian grand prix", "italian grand prix", "japanese grand prix", "malaysian grand prix", "monaco grand prix", "new zealand grand prix", "spanish grand prix", "turkish grand prix", "united states grand prix"], "date": ["march 18", "april 15", "september 16", "october 21", "july 8", "june 10", "october 7", "july 1", "august 5", "september 9", "september 30", "april 8", "may 27", "march 13", "may 13", "august 26", "june 17"], "venue": ["albert park grand prix circuit", "bahrain international circuit", "circuit de spa - francorchamps", "autódromo josé carlos pace", "silverstone circuit", "circuit gilles villeneuve", "shanghai international circuit", "circuit de nevers magny - cours", "hungaroring", "autodromo nazionale monza", "fuji speedway", "sepang international circuit", "circuit de monaco", "teretonga park", "circuit de catalunya", "istanbul park", "indianapolis motor speedway"], "winner": ["kimi räikkönen", "felipe massa", "kimi räikkönen", "kimi räikkönen", "kimi räikkönen", "lewis hamilton", "kimi räikkönen", "kimi räikkönen", "lewis hamilton", "fernando alonso", "lewis hamilton", "fernando alonso", "fernando alonso", "daniel gaunt", "felipe massa", "felipe massa", "lewis hamilton"], "notes": ["world championship formula 1", "world championship formula 1", "world championship formula 1", "world championship formula 1", "world championship formula 1", "world championship formula 1", "world championship formula 1", "world championship formula 1", "world championship formula 1", "world championship formula 1", "world championship formula 1", "world championship formula 1", "world championship formula 1", "toyota racing series", "world championship formula 1", "world championship formula 1", "world championship formula 1"]}