{"name": ["citizens bank building", "tampa city hall", "floridan hotel", "franklin exchange building", "park tower", "one tampa city center", "bank of america tower", "100 north tampa"], "street address": ["701 north franklin street", "315 john f kennedy boulevard", "905 franklin street", "655 north franklin street", "400 north tampa street", "201 north franklin street", "101 east kennedy boulevard", "100 north tampa street"], "years as tallest": ["1913 - 1915", "1915 - 1926", "1926 - 1966", "1966 - 1972", "1972 - 1981", "1981 - 1986", "1986 - 1992", "1992 - present"], "height ft (m)": ["145 (44)", "160 (49)", "204 (62)", "280 (85)", "458 (140)", "537 (164)", "577 (176)", "579 (177)"], "floors": ["12", "10", "17", "22", "36", "39", "42", "42"]}