{"monday": ["mike north (begins 10 pm sunday)", "jt the brick", "fox sports daybreak", "the dan patrick show", "jay mohr sports", "fox sports primetime", "petros & money", "fox sports tonight (ends 1 am next day)", "monday"], "tuesday": ["fox sports tonight (begins 10 pm day before)", "jt the brick", "fox sports daybreak", "the dan patrick show", "jay mohr sports", "fox sports primetime", "petros & money", "fox sports tonight (ends 1 am next day)", "tuesday"], "wednesday": ["fox sports tonight (begins 10 pm day before)", "jt the brick", "fox sports daybreak", "the dan patrick show", "jay mohr sports", "fox sports primetime", "petros & money", "fox sports tonight (ends 1 am next day)", "wednesday"], "thursday": ["fox sports tonight (begins 10 pm day before)", "jt the brick", "fox sports daybreak", "the dan patrick show", "jay mohr sports", "fox sports primetime", "petros & money", "fox sports tonight (ends 1 am next day)", "thursday"], "friday": ["fox sports tonight (begins 10 pm day before)", "jt the brick", "fox sports daybreak", "the dan patrick show", "jay mohr sports", "fox sports primetime", "petros & money", "fox sports tonight (ends 1 am next day)", "friday"]}