{"rank": ["1", "2", "3", "4", "5", "6", "7", "8", "9", "10", "11", "12", "12", "14", "15", "16", "17", "18", "19", "19", "19", "22", "22", "23", "total"], "nation": ["great britain (gbr)", "united states (usa)", "australia (aus)", "germany (ger)", "spain (esp)", "czech republic (cze)", "italy (ita)", "switzerland (sui)", "japan (jpn)", "france (fra)", "south africa (rsa)", "austria (aut)", "belarus (blr)", "new zealand (nzl)", "poland (pol)", "china (chn)", "netherlands (ned)", "south korea (kor)", "finland (fin)", "romania (rou)", "slovakia (svk)", "canada (can)", "lebanon (lib)", "belgium (bel)", "total"], "gold": ["17", "5", "3", "3", "3", "2", "2", "2", "1", "1", "1", "1", "1", "1", "1", "0", "0", "0", "0", "0", "0", "0", "0", "0", "44"], "silver": ["3", "4", "5", "6", "5", "2", "1", "0", "3", "1", "1", "1", "1", "0", "0", "3", "3", "1", "1", "1", "1", "0", "0", "0", "44"], "bronze": ["0", "4", "7", "4", "3", "4", "3", "0", "2", "2", "1", "0", "0", "3", "1", "4", "0", "1", "0", "0", "0", "2", "2", "1", "44"], "total": ["20", "13", "15", "13", "11", "8", "6", "2", "6", "4", "3", "2", "2", "4", "2", "7", "3", "2", "1", "1", "1", "2", "2", "1", "132"]}