{"election": ["1832", "1834", "1835", "1843 by - election", "1848 by - election", "1857", "1859", "1865", "1866 by - election", "1867 by - election", "1876 by - election", "1885"], "first member": ["sir rowland hill , bt", "sir rowland hill , bt", "sir rowland hill , bt", "viscount clive", "john whitehall dod", "john whitehall dod", "john ormsby - gore", "john ormsby - gore", "john ormsby - gore", "john ormsby - gore", "stanley leighton", "constituency abolished"], "first party": ["tory", "conservative", "conservative", "conservative", "conservative", "conservative", "conservative", "conservative", "conservative", "conservative", "conservative", "constituency abolished"], "second member": ["john cotes", "john cotes", "william ormsby - gore", "william ormsby - gore", "william ormsby - gore", "hon rowland hill", "hon rowland hill", "hon charles cust", "hon adelbert brownlow - cust", "viscount newport", "viscount newport", "constituency abolished"], "second party": ["whig", "whig", "conservative", "conservative", "conservative", "conservative", "conservative", "conservative", "conservative", "conservative", "conservative", "constituency abolished"]}