{"name": ["01f", "02f", "03f", "04f", "05f", "06f", "07f", "hettie", "09f", "innis", "joni", "ken", "jasper", "lin", "15f", "season aggregates", "15systems"], "dates active": ["december 1 - 2", "december 3 - 7", "december 10 - 11", "january 4 - 14", "january 11 - 14", "january 19 - 23", "january 23 - 25", "january 24 - 31", "february 1 - 5", "february 13 - 18", "march 10 - 14", "march 16 - 19", "march 24 - 30", "march 31 - april 7", "april 7 - 10", "season aggregates", "december 1 - april 10"], "windspeeds": ["unknown", "unknown", "unknown", "unknown", "unknown", "unknown", "unknown", "n /a", "55 km / h (35 mph)", "75 km / h (45 mph)", "95 km / h (60 mph)", "95 km / h (60 mph)", "100 km / h (60 mph)", "110 km / h (70 mph)", "35 km / h (25 mph)", "season aggregates", "110 km / h (70 mph)"], "pressure": ["hpa (inhg)", "hpa (inhg)", "hpa (inhg)", "hpa (inhg)", "hpa (inhg)", "hpa (inhg)", "hpa (inhg)", "hpa (inhg)", "hpa (inhg)", "hpa (inhg)", "hpa (inhg)", "hpa (inhg)", "hpa (inhg)", "hpa (inhg)", "hpa (inhg)", "season aggregates", "975hpa (28.81inhg)"], "deaths": ["none", "none", "none", "none", "none", "none", "none", "none", "unknown", "1", "unknown", "none", "none", "none", "none", "season aggregates", "none"]}