{"place": ["t1", "t1", "t3", "t3", "t5", "t5", "t5", "t5", "t9", "t9", "t9", "t9", "t9", "t9", "t9"], "player": ["scott dunlap", "tiger woods", "darren clarke", "davis love iii", "stephen ames", "ed fryatt", "fred funk", "j p hayes", "stuart appleby", "brian henninger", "miguel ángel jiménez", "jonathan kaye", "tom kite", "phil mickelson", "jean van de velde"], "country": ["united states", "united states", "northern ireland", "united states", "trinidad and tobago", "england", "united states", "united states", "australia", "united states", "spain", "united states", "united states", "united states", "france"], "score": ["66", "66", "68", "68", "69", "69", "69", "69", "70", "70", "70", "70", "70", "70", "70"], "to par": ["- 6", "- 6", "- 4", "- 4", "- 3", "- 3", "- 3", "- 3", "- 2", "- 2", "- 2", "- 2", "- 2", "- 2", "- 2"]}